colossalai/__init__.py
colossalai/initialize.py
colossalai/_C/__init__.py
colossalai/_analyzer/__init__.py
colossalai/_analyzer/envs.py
colossalai/_analyzer/_subclasses/__init__.py
colossalai/_analyzer/_subclasses/_meta_registration.py
colossalai/_analyzer/_subclasses/_monkey_patch.py
colossalai/_analyzer/_subclasses/flop_tensor.py
colossalai/_analyzer/_subclasses/meta_tensor.py
colossalai/_analyzer/fx/__init__.py
colossalai/_analyzer/fx/codegen.py
colossalai/_analyzer/fx/graph_module.py
colossalai/_analyzer/fx/node_util.py
colossalai/_analyzer/fx/symbolic_profile.py
colossalai/_analyzer/fx/passes/__init__.py
colossalai/_analyzer/fx/passes/graph_profile.py
colossalai/_analyzer/fx/passes/shape_prop.py
colossalai/_analyzer/fx/tracer/__init__.py
colossalai/_analyzer/fx/tracer/bias_addition.py
colossalai/_analyzer/fx/tracer/custom_leaf_module.py
colossalai/_analyzer/fx/tracer/proxy.py
colossalai/_analyzer/fx/tracer/symbolic_trace.py
colossalai/_analyzer/fx/tracer/tracer.py
colossalai/accelerator/__init__.py
colossalai/accelerator/api.py
colossalai/accelerator/base_accelerator.py
colossalai/accelerator/cpu_accelerator.py
colossalai/accelerator/cuda_accelerator.py
colossalai/accelerator/npu_accelerator.py
colossalai/amp/__init__.py
colossalai/amp/naive_amp/__init__.py
colossalai/amp/naive_amp/mixed_precision_optimizer.py
colossalai/amp/naive_amp/grad_scaler/__init__.py
colossalai/amp/naive_amp/grad_scaler/base_grad_scaler.py
colossalai/amp/naive_amp/grad_scaler/constant_grad_scaler.py
colossalai/amp/naive_amp/grad_scaler/dynamic_grad_scaler.py
colossalai/amp/naive_amp/mixed_precision_mixin/__init__.py
colossalai/amp/naive_amp/mixed_precision_mixin/base.py
colossalai/amp/naive_amp/mixed_precision_mixin/bf16.py
colossalai/amp/naive_amp/mixed_precision_mixin/fp16.py
colossalai/auto_parallel/__init__.py
colossalai/auto_parallel/checkpoint/__init__.py
colossalai/auto_parallel/checkpoint/build_c_ext.py
colossalai/auto_parallel/checkpoint/ckpt_solver_base.py
colossalai_nightly-2024.2.19.dist-info/LICENSE
colossalai_nightly-2024.2.19.dist-info/METADATA
colossalai_nightly-2024.2.19.dist-info/WHEEL
colossalai_nightly-2024.2.19.dist-info/entry_points.txt
colossalai_nightly-2024.2.19.dist-info/top_level.txt
colossalai_nightly-2024.2.19.dist-info/RECORD
