Metadata-Version: 2.1
Name: colossalai-nightly
Version: 2024.2.19
Summary: An integrated large-scale model training system with efficient parallelization techniques
Home-page: https://www.colossalai.org
License: Apache Software License 2.0
Project-URL: Forum, https://github.com/hpcaitech/ColossalAI/discussions
Project-URL: Bug Tracker, https://github.com/hpcaitech/ColossalAI/issues
Project-URL: Examples, https://github.com/hpcaitech/ColossalAI-Examples
Project-URL: Documentation, http://colossalai.readthedocs.io
Project-URL: Github, https://github.com/hpcaitech/ColossalAI
Platform: UNKNOWN
Classifier: Programming Language :: Python :: 3
Classifier: License :: OSI Approved :: Apache Software License
Classifier: Environment :: GPU :: NVIDIA CUDA
Classifier: Topic :: Scientific/Engineering :: Artificial Intelligence
Classifier: Topic :: System :: Distributed Computing
Requires-Python: >=3.6
Requires-Dist: numpy
Requires-Dist: tqdm
Requires-Dist: psutil
Requires-Dist: packaging
Requires-Dist: pre-commit
Requires-Dist: rich
Requires-Dist: click
Requires-Dist: fabric
Requires-Dist: contexttimer
Requires-Dist: ninja
Requires-Dist: torch >=1.12
Requires-Dist: safetensors
Requires-Dist: einops
Requires-Dist: pydantic
Requires-Dist: ray
Requires-Dist: sentencepiece
Requires-Dist: google
Requires-Dist: protobuf
